pydataviz_cleaner/__init__.py
pydataviz_cleaner/cleaner.py
pydataviz_cleaner/report.py
pydataviz_cleaner-0.0.3.dist-info/licenses/LICENSE
pydataviz_cleaner-0.0.3.dist-info/METADATA
pydataviz_cleaner-0.0.3.dist-info/WHEEL
pydataviz_cleaner-0.0.3.dist-info/top_level.txt
pydataviz_cleaner-0.0.3.dist-info/RECORD
