Metadata-Version: 2.4
Name: pydataviz_cleaner
Version: 0.0.3
Summary: A lightweight Python package to clean messy data for visualization.
Author-email: Saifur Rahman <saifurnstuiit223344@gmail.com>
License: MIT
Requires-Python: >=3.8
License-File: LICENSE
Requires-Dist: pandas
Dynamic: license-file
